blinky.v
// this will be a module to access a 1Mx8 SRAM / flash module such as I own for soldering practice. They will be useful for
// testing data structure acceleration, too, I reckon.

`default_nettype none

// FOR STARTERS JUST USING CLIFFORD WOLF'S BLINKY
module blinky(
    input wire i_clk,
    output wire o_led       //temp debug
    //here will go all the address and data lines and stuff - make the addr width variable
    );

    parameter CBITS = 26;

    //here will go all the address and data lines and stuff

    reg	[CBITS-1:0]	counter = 0;
    always @(posedge i_clk)
    counter <= counter + 1'b1;
    assign o_led = counter[CBITS-1];
endmodule

top_test.v
//seeing if this is how to do a testbench for a module

`default_nettype none



//`include "sram.v"

// FOR STARTERS JUST USING CLIFFORD WOLF'S BLINKY
module top_test();
    //and then the clock, simulation style
    reg clk = 1;
    //make easier-to-count gtkwave values by having a system tick be 10 clk ticks
    always #5 clk = (clk === 1'b0);

    wire led_b_outwire;
    reg led_reg = 0;

    //then the sram module proper, currently a blinkois
    //let us have it blink on the blue upduino LED.
    // test using smaller counter so we don't have to run a jillion cycles in gtkwave
    // ....well, this module should always be compiled with TEST defined but... wev
    `ifdef TEST
    parameter cbits = 4;
    `else
    parameter cbits = 26;
    `endif
    blinky #(.CBITS(cbits)) ram(.i_clk(clk),.o_led(led_b_outwire));

    always @(posedge clk) begin
        //this should drive the blinkingness
        led_reg <= led_b_outwire;
    end

    //bit for creating gtkwave output
    /* dunno if we need this with the makefile version - Maybe, it's hanging - aha, bc I hadn't made clean and had a non-finishing version */
    initial begin
        //uncomment the next two for gtkwave?
        $dumpfile("top_test.vcd");
        $dumpvars(0, top_test);
    end

    initial begin
        $display("and away we go!!!1");
        #1000 $finish;           //longer sim, mask clock is now 16 bits. 5 sec run on vm, 30M vcd.
    end

endmodule

top_test.vcd
$date
	Sat Nov 23 17:37:56 2019
$end
$version
	Icarus Verilog
$end
$timescale
	1s
$end
$scope module top_test $end
$var wire 1 ! led_b_outwire $end
$var reg 1 " clk $end
$var reg 1 # led_reg $end
$scope module ram $end
$var wire 1 " i_clk $end
$var wire 1 ! o_led $end
$var reg 4 $ counter [3:0] $end
$upscope $end
$upscope $end
$enddefinitions $end
#0
$dumpvars
b1 $
0#
1"
0!
$end
#5
0"
#10
b10 $
1"
#15
0"
#20
b11 $
1"
#25
0"
#30
b100 $
1"
#35
0"
#40
b101 $
1"
#45
0"
#50
b110 $
1"
#55
0"
#60
b111 $
1"
#65
0"
#70
1!
b1000 $
1"
#75
0"
#80
b1001 $
1#
1"
#85
0"
#90
b1010 $
1"
#95
0"
#100
b1011 $
1"
#105
0"
#110
b1100 $
1"
#115
0"
#120
b1101 $
1"
#125
0"
#130
b1110 $
1"
#135
0"
#140
b1111 $
1"
#145
0"
#150
0!
b0 $
1"
#155
0"
#160
b1 $
0#
1"
#165
0"
#170
b10 $
1"
#175
0"
#180
b11 $
1"
#185
0"
#190
b100 $
1"
#195
0"
#200
b101 $
1"
#205
0"
#210
b110 $
1"
#215
0"
#220
b111 $
1"
#225
0"
#230
1!
b1000 $
1"
#235
0"
#240
b1001 $
1#
1"
#245
0"
#250
b1010 $
1"
#255
0"
#260
b1011 $
1"
#265
0"
#270
b1100 $
1"
#275
0"
#280
b1101 $
1"
#285
0"
#290
b1110 $
1"
#295
0"
#300
b1111 $
1"
#305
0"
#310
0!
b0 $
1"
#315
0"
#320
b1 $
0#
1"
#325
0"
#330
b10 $
1"
#335
0"
#340
b11 $
1"
#345
0"
#350
b100 $
1"
#355
0"
#360
b101 $
1"
#365
0"
#370
b110 $
1"
#375
0"
#380
b111 $
1"
#385
0"
#390
1!
b1000 $
1"
#395
0"
#400
b1001 $
1#
1"
#405
0"
#410
b1010 $
1"
#415
0"
#420
b1011 $
1"
#425
0"
#430
b1100 $
1"
#435
0"
#440
b1101 $
1"
#445
0"
#450
b1110 $
1"
#455
0"
#460
b1111 $
1"
#465
0"
#470
0!
b0 $
1"
#475
0"
#480
b1 $
0#
1"
#485
0"
#490
b10 $
1"
#495
0"
#500
b11 $
1"
#505
0"
#510
b100 $
1"
#515
0"
#520
b101 $
1"
#525
0"
#530
b110 $
1"
#535
0"
#540
b111 $
1"
#545
0"
#550
1!
b1000 $
1"
#555
0"
#560
b1001 $
1#
1"
#565
0"
#570
b1010 $
1"
#575
0"
#580
b1011 $
1"
#585
0"
#590
b1100 $
1"
#595
0"
#600
b1101 $
1"
#605
0"
#610
b1110 $
1"
#615
0"
#620
b1111 $
1"
#625
0"
#630
0!
b0 $
1"
#635
0"
#640
b1 $
0#
1"
#645
0"
#650
b10 $
1"
#655
0"
#660
b11 $
1"
#665
0"
#670
b100 $
1"
#675
0"
#680
b101 $
1"
#685
0"
#690
b110 $
1"
#695
0"
#700
b111 $
1"
#705
0"
#710
1!
b1000 $
1"
#715
0"
#720
b1001 $
1#
1"
#725
0"
#730
b1010 $
1"
#735
0"
#740
b1011 $
1"
#745
0"
#750
b1100 $
1"
#755
0"
#760
b1101 $
1"
#765
0"
#770
b1110 $
1"
#775
0"
#780
b1111 $
1"
#785
0"
#790
0!
b0 $
1"
#795
0"
#800
b1 $
0#
1"
#805
0"
#810
b10 $
1"
#815
0"
#820
b11 $
1"
#825
0"
#830
b100 $
1"
#835
0"
#840
b101 $
1"
#845
0"
#850
b110 $
1"
#855
0"
#860
b111 $
1"
#865
0"
#870
1!
b1000 $
1"
#875
0"
#880
b1001 $
1#
1"
#885
0"
#890
b1010 $
1"
#895
0"
#900
b1011 $
1"
#905
0"
#910
b1100 $
1"
#915
0"
#920
b1101 $
1"
#925
0"
#930
b1110 $
1"
#935
0"
#940
b1111 $
1"
#945
0"
#950
0!
b0 $
1"
#955
0"
#960
b1 $
0#
1"
#965
0"
#970
b10 $
1"
#975
0"
#980
b11 $
1"
#985
0"
#990
b100 $
1"
#995
0"
#1000
b101 $
1"
